<?xml version="1.0" encoding="UTF-8"?>
<databaseChangeLog
        xmlns="http://www.liquibase.org/xml/ns/dbchangelog"
        xmlns:xsi="http://www.w3.org/2001/XMLSchema-instance"
        xsi:schemaLocation="http://www.liquibase.org/xml/ns/dbchangelog
        http://www.liquibase.org/xml/ns/dbchangelog/dbchangelog-4.2.xsd">

    <changeSet id="6" author="Yakushev">

        <createTable tableName="statuses">
            <column name="id" type="int" autoIncrement="true">
                <constraints primaryKey="true" nullable="false"></constraints>
            </column>
            <column name="status_name" type="varchar(100)">
                <constraints nullable="false" unique="true"/>
            </column>
        </createTable>

        <insert tableName="statuses">
            <column name="status_name" value="Передать на оплату"/>
        </insert>
        <insert tableName="statuses">
            <column name="status_name" value="Забрать оригиналы на оплату"/>
        </insert>
        <insert tableName="statuses">
            <column name="status_name" value="Передать оригиналы на оплату"/>
        </insert>
        <insert tableName="statuses">
            <column name="status_name" value="Подписать акт сверки"/>
        </insert>


    </changeSet>

</databaseChangeLog>